mdx_staticfiles.py
mdx_staticfiles-0.1.dist-info/LICENSE
mdx_staticfiles-0.1.dist-info/METADATA
mdx_staticfiles-0.1.dist-info/WHEEL
mdx_staticfiles-0.1.dist-info/top_level.txt
mdx_staticfiles-0.1.dist-info/RECORD
