Metadata-Version: 2.1
Name: mdx-staticfiles
Version: 0.1
Summary: A django.contrib.staticfiles extension for Markdown
Home-page: http://github.com/CTPUG/mdx_staticfiles
Author: CTPUG
Author-email: ctpug@googlegroups.com
License: MIT
Platform: UNKNOWN
Classifier: Development Status :: 4 - Beta
Classifier: Intended Audience :: Developers
Classifier: License :: OSI Approved :: MIT License
Classifier: Operating System :: POSIX
Classifier: Programming Language :: Python
Classifier: Programming Language :: Python :: 3
Classifier: Programming Language :: Python :: 3.6
Classifier: Programming Language :: Python :: 3.7
Classifier: Programming Language :: Python :: 3.8
Classifier: Programming Language :: Python :: 3.9
Classifier: Framework :: Django
Classifier: Topic :: Software Development :: Libraries :: Python Modules
Classifier: Topic :: Internet :: WWW/HTTP
Requires-Dist: Django
Requires-Dist: markdown
